{
  "info": {
    "title": "research.galacticraft.circuit_fabricator",
    "description": "research.galacticraft.circuit_fabricator.desc",
    "items_to_render": [
      "galacticraft:circuit_fabricator"
    ],
    "tier": 1
  },
  "parents": [
    "galacticraft:coal_generator",
    "galacticraft:aluminum_wire"
  ],
  "criteria": {
    "coal_gen": {
      "trigger": "minecraft:inventory_changed",
      "conditions": {
        "items": [
          {
            "item": "galacticraft:circuit_fabricator"
          }
        ]
      }
    }
  },
  "requirements": [
    [
      "coal_gen"
    ]
  ],
  "rewards": {
    "rocket_parts": [
      "galacticraft:default_fin"
    ]
  }
}